CVutils/Timer.py
CVutils/__init__.py
CVutils/anno_formater.py
CVutils/db_control.py
CVutils/loader.py
CVutils/logger.py
CVutils/preprocessor.py
CVutils/saver.py
CVutils/slack_api.py
CVutils/type_converter.py
CVutils/utils.py
CVutils/video_processor.py
CVutils/visualize.py
Computer_vision_utils-0.0.1.dist-info/METADATA
Computer_vision_utils-0.0.1.dist-info/WHEEL
Computer_vision_utils-0.0.1.dist-info/top_level.txt
Computer_vision_utils-0.0.1.dist-info/RECORD
